scrapy_nimble/__init__.py
scrapy_nimble/middlewares.py
scrapy_nimble-0.0.2.dist-info/METADATA
scrapy_nimble-0.0.2.dist-info/WHEEL
scrapy_nimble-0.0.2.dist-info/licenses/LICENSE
scrapy_nimble-0.0.2.dist-info/RECORD
