Metadata-Version: 2.1
Name: scrapy-nimble
Version: 0.0.2
Summary: Scrapy Downloader Middleware that helps to integrate Scrapy with Nimble Web API.
Project-URL: Homepage, https://github.com/rennerocha/scrapy-nimble
Project-URL: Issues, https://github.com/rennerocha/scrapy-nimble/issues
Author-email: Renne Rocha <renne@rocha.dev.br>
Maintainer-email: Renne Rocha <renne@rocha.dev.br>
License-File: LICENSE
Classifier: Development Status :: 4 - Beta
Classifier: Intended Audience :: Developers
Classifier: License :: OSI Approved :: MIT License
Classifier: Operating System :: OS Independent
Classifier: Programming Language :: Python :: 3
Requires-Python: >=3.8
Requires-Dist: scrapy
Provides-Extra: test
Requires-Dist: pytest; extra == 'test'
